zarrbench/__init__.py
zarrbench/__main__.py
zarrbench/bench.py
zarrbench/py.typed
zarrbench-0.1.1.dist-info/METADATA
zarrbench-0.1.1.dist-info/WHEEL
zarrbench-0.1.1.dist-info/entry_points.txt
zarrbench-0.1.1.dist-info/RECORD
