Metadata-Version: 2.3
Name: zarrbench
Version: 0.1.1
Summary: Measure request handling performance of HTTP servers serving zarr datasets.
Author-email: Tobias Kölling <tobias.koelling@mpimet.mpg.de>
Requires-Python: >=3.10
Requires-Dist: aiohttp>=3.10.10
Requires-Dist: certifi>=2024.8.30
Requires-Dist: humanize>=4.11.0
Requires-Dist: numpy>=2.1.2
Requires-Dist: rich>=13.9.3
